noisegrad/__init__.py
noisegrad/explainers.py
noisegrad/noisegrad.py
noisegrad/py.typed
noisegrad/utils.py
noisegrad-0.0.4.dist-info/LICENSE.md
noisegrad-0.0.4.dist-info/WHEEL
noisegrad-0.0.4.dist-info/METADATA
noisegrad-0.0.4.dist-info/RECORD
