Metadata-Version: 2.1
Name: noisegrad
Version: 0.0.4
Summary: A explanation enhancement method.
Keywords: explainable ai,xai,machine learning,deep learning
Author-email: Kirill Bykov <kirill.bykov@campus.tu-berlin.de>, Anna Hedström <anna.hedstroem@tu-berlin.de>, Shinichi Nakajima <nakajima@tu-berlin.de>, "Marina M.-C. Höhne" <marina.hoehne@tu-berlin.de>, Artem Sereda <artem.sereda@campus.tu-berlin.de>
Maintainer-email: Kirill Bykov <kirill.bykov@campus.tu-berlin.de>, Anna Hedström <anna.hedstroem@tu-berlin.de>, Artem Sereda <artem.sereda@campus.tu-berlin.de>
Requires-Python: >=3.8
Classifier: Development Status :: 3 - Alpha
Classifier: Intended Audience :: Education
Classifier: Intended Audience :: Science/Research
Classifier: Intended Audience :: Developers
Classifier: Programming Language :: Python :: 3 :: Only
Classifier: Topic :: Software Development :: Libraries :: Python Modules
Classifier: Topic :: Scientific/Engineering :: Artificial Intelligence
Requires-Dist: torch>=1.13.1
Requires-Dist: numpy
Requires-Dist: tqdm
Requires-Dist: captum>=0.6.0 ; extra == "examples"
Requires-Dist: matplotlib ; extra == "examples"
Requires-Dist: torchvision==0.14.1 ; extra == "examples"
Requires-Dist: transformers>=4.26.0 ; extra == "examples"
Requires-Dist: datasets==2.9.0 ; extra == "examples"
Requires-Dist: noisegrad[examples] ; extra == "lint"
Requires-Dist: flake8 ; extra == "lint"
Requires-Dist: mypy ; extra == "lint"
Requires-Dist: noisegrad[examples] ; extra == "test"
Requires-Dist: pytest ; extra == "test"
Project-URL: Homepage, https://github.com/understandable-machine-intelligence-lab/NoiseGrad
Provides-Extra: examples
Provides-Extra: lint
Provides-Extra: test
